{
  "groupMenu": "E-Money",
  "data": [
    {
      "nama": "EMONEY BNI",
      "image": "http://192.168.5.6/api/image/app/e-money/emoney_bni.png",
      "kode_operator": "EBNI",
      "hint": "Contoh : 1221102174",
      "hintTitle": "Nomor ID/Kartu",
      "keyboardNomor": true,
      "detail": [
        {
          "keterangan": "TAPCASH BNI 10.000",
          "kodeTransaksi": "EBNI10",
          "status": "",
          "kategori": "TAPCASH",
          "harga": "Rp. 10.550",
          "hargaInt": 10500,
          "ket": "",
          "nominal": "TAPCASH BNI",
          "urutan": 0,
          "poin": "0"
        },
        {
          "keterangan": "TAPCASH BNI 20.000",
          "kodeTransaksi": "EBNI20",
          "status": "",
          "kategori": "TAPCASH",
          "harga": "Rp. 20.550",
          "hargaInt": 20500,
          "ket": "",
          "nominal": "TAPCASH BNI",
          "urutan": 0,
          "poin": "0"
        },
        {
          "keterangan": "TAPCASH BNI 25.000",
          "kodeTransaksi": "EBNI25",
          "status": "",
          "kategori": "TAPCASH",
          "harga": "Rp. 25.550",
          "hargaInt": 25500,
          "ket": "",
          "nominal": "TAPCASH BNI",
          "urutan": 0,
          "poin": "0"
        },
        {
          "keterangan": "TAPCASH BNI 50.000",
          "kodeTransaksi": "EBNI50",
          "status": "",
          "kategori": "TAPCASH",
          "harga": "Rp. 50.550",
          "hargaInt": 50500,
          "ket": "",
          "nominal": "TAPCASH BNI",
          "urutan": 0,
          "poin": "0"
        },
        {
          "keterangan": "TAPCASH BNI 100.000",
          "kodeTransaksi": "EBNI100",
          "status": "",
          "kategori": "TAPCASH",
          "harga": "Rp. 100.550",
          "hargaInt": 100500,
          "ket": "",
          "nominal": "TAPCASH BNI",
          "urutan": 0,
          "poin": "0"
        },
        {
          "keterangan": "TAPCASH BNI 150.000",
          "kodeTransaksi": "EBNI150",
          "status": "",
          "kategori": "TAPCASH",
          "harga": "Rp. 150.550",
          "hargaInt": 150500,
          "ket": "",
          "nominal": "TAPCASH BNI",
          "urutan": 0,
          "poin": "0"
        },
        {
          "keterangan": "TAPCASH BNI 200.000",
          "kodeTransaksi": "EBNI200",
          "status": "",
          "kategori": "TAPCASH",
          "harga": "Rp. 200.550",
          "hargaInt": 200500,
          "ket": "",
          "nominal": "TAPCASH BNI",
          "urutan": 0,
          "poin": "0"
        },
        {
          "keterangan": "TAPCASH BNI 250.000",
          "kodeTransaksi": "EBNI250",
          "status": "",
          "kategori": "TAPCASH",
          "harga": "Rp. 250.550",
          "hargaInt": 250500,
          "ket": "",
          "nominal": "TAPCASH BNI",
          "urutan": 0,
          "poin": "0"
        },
        {
          "keterangan": "TAPCASH BNI 300.000",
          "kodeTransaksi": "EBNI300",
          "status": "",
          "kategori": "TAPCASH",
          "harga": "Rp. 300.550",
          "hargaInt": 300500,
          "ket": "",
          "nominal": "TAPCASH BNI",
          "urutan": 0,
          "poin": "0"
        },
        {
          "keterangan": "TAPCASH BNI 500.000",
          "kodeTransaksi": "EBNI500",
          "status": "",
          "kategori": "TAPCASH",
          "harga": "Rp. 500.550",
          "hargaInt": 500500,
          "ket": "",
          "nominal": "TAPCASH BNI",
          "urutan": 0,
          "poin": "0"
        }
      ]
    },
    {
      "nama": "EMONEY BOOST",
      "image": "http://192.168.5.6/api/image/app/e-money/emoney_boost.png",
      "kode_operator": "BOOST",
      "hint": "Contoh : 081234567890",
      "hintTitle": "Nomor Handphone",
      "keyboardNomor": true,
      "detail": [
        {
          "keterangan": "SALDO BOOST 10,000",
          "kodeTransaksi": "BOOST10",
          "status": "",
          "kategori": "SALDO",
          "harga": "Rp. 10.550",
          "hargaInt": 10500,
          "ket": "",
          "nominal": "SALDO BOOST ,",
          "urutan": 0,
          "poin": "0"
        },
        {
          "keterangan": "SALDO BOOST 20,000",
          "kodeTransaksi": "BOOST20",
          "status": "",
          "kategori": "SALDO",
          "harga": "Rp. 20.550",
          "hargaInt": 20500,
          "ket": "",
          "nominal": "SALDO BOOST ,",
          "urutan": 0,
          "poin": "0"
        },
        {
          "keterangan": "SALDO BOOST 25,000",
          "kodeTransaksi": "BOOST25",
          "status": "",
          "kategori": "SALDO",
          "harga": "Rp. 25.550",
          "hargaInt": 25500,
          "ket": "",
          "nominal": "SALDO BOOST ,",
          "urutan": 0,
          "poin": "0"
        },
        {
          "keterangan": "SALDO BOOST 50,000",
          "kodeTransaksi": "BOOST50",
          "status": "",
          "kategori": "SALDO",
          "harga": "Rp. 50.550",
          "hargaInt": 50500,
          "ket": "",
          "nominal": "SALDO BOOST ,",
          "urutan": 0,
          "poin": "0"
        },
        {
          "keterangan": "SALDO BOOST 100,000",
          "kodeTransaksi": "BOOST100",
          "status": "",
          "kategori": "SALDO",
          "harga": "Rp. 100.550",
          "hargaInt": 100500,
          "ket": "",
          "nominal": "SALDO BOOST ,",
          "urutan": 0,
          "poin": "0"
        },
        {
          "keterangan": "SALDO BOOST 150,000",
          "kodeTransaksi": "BOOST150",
          "status": "",
          "kategori": "SALDO",
          "harga": "Rp. 150.550",
          "hargaInt": 150500,
          "ket": "",
          "nominal": "SALDO BOOST ,",
          "urutan": 0,
          "poin": "0"
        },
        {
          "keterangan": "SALDO BOOST 200,000",
          "kodeTransaksi": "BOOST200",
          "status": "",
          "kategori": "SALDO",
          "harga": "Rp. 200.550",
          "hargaInt": 200500,
          "ket": "",
          "nominal": "SALDO BOOST ,",
          "urutan": 0,
          "poin": "0"
        },
        {
          "keterangan": "SALDO BOOST 250,000",
          "kodeTransaksi": "BOOST250",
          "status": "",
          "kategori": "SALDO",
          "harga": "Rp. 250.550",
          "hargaInt": 250500,
          "ket": "",
          "nominal": "SALDO BOOST ,",
          "urutan": 0,
          "poin": "0"
        },
        {
          "keterangan": "SALDO BOOST 300,000",
          "kodeTransaksi": "BOOST300",
          "status": "",
          "kategori": "SALDO",
          "harga": "Rp. 300.550",
          "hargaInt": 300500,
          "ket": "",
          "nominal": "SALDO BOOST ,",
          "urutan": 0,
          "poin": "0"
        },
        {
          "keterangan": "SALDO BOOST 500,000",
          "kodeTransaksi": "BOOST500",
          "status": "",
          "kategori": "SALDO",
          "harga": "Rp. 500.550",
          "hargaInt": 500500,
          "ket": "",
          "nominal": "SALDO BOOST ,",
          "urutan": 0,
          "poin": "0"
        }
      ]
    },
    {
      "nama": "EMONEY UNIKQU",
      "image": "http://192.168.5.6/api/image/app/e-money/emoney_unikqu.png",
      "kode_operator": "EMUNIKQU",
      "hint": "Contoh : 081234567890",
      "hintTitle": "Nomor Handphone",
      "keyboardNomor": true,
      "detail": [
        {
          "keterangan": "SALDO UNIKQU 10,000",
          "kodeTransaksi": "UNIKQU10",
          "status": "",
          "kategori": "SALDO",
          "harga": "Rp. 10.550",
          "hargaInt": 10500,
          "ket": "",
          "nominal": "SALDO UNIKQU ,",
          "urutan": 0,
          "poin": "0"
        },
        {
          "keterangan": "SALDO UNIKQU 20,000",
          "kodeTransaksi": "UNIKQU20",
          "status": "",
          "kategori": "SALDO",
          "harga": "Rp. 20.550",
          "hargaInt": 20500,
          "ket": "",
          "nominal": "SALDO UNIKQU ,",
          "urutan": 0,
          "poin": "0"
        },
        {
          "keterangan": "SALDO UNIKQU 25,000",
          "kodeTransaksi": "UNIKQU25",
          "status": "",
          "kategori": "SALDO",
          "harga": "Rp. 25.550",
          "hargaInt": 25500,
          "ket": "",
          "nominal": "SALDO UNIKQU ,",
          "urutan": 0,
          "poin": "0"
        },
        {
          "keterangan": "SALDO UNIKQU 50,000",
          "kodeTransaksi": "UNIKQU50",
          "status": "",
          "kategori": "SALDO",
          "harga": "Rp. 50.550",
          "hargaInt": 50500,
          "ket": "",
          "nominal": "SALDO UNIKQU ,",
          "urutan": 0,
          "poin": "0"
        },
        {
          "keterangan": "SALDO UNIKQU 100,000",
          "kodeTransaksi": "UNIKQU100",
          "status": "",
          "kategori": "SALDO",
          "harga": "Rp. 100.550",
          "hargaInt": 100500,
          "ket": "",
          "nominal": "SALDO UNIKQU ,",
          "urutan": 0,
          "poin": "0"
        },
        {
          "keterangan": "SALDO UNIKQU 150,000",
          "kodeTransaksi": "UNIKQU150",
          "status": "",
          "kategori": "SALDO",
          "harga": "Rp. 150.550",
          "hargaInt": 150500,
          "ket": "",
          "nominal": "SALDO UNIKQU ,",
          "urutan": 0,
          "poin": "0"
        },
        {
          "keterangan": "SALDO UNIKQU 200,000",
          "kodeTransaksi": "UNIKQU200",
          "status": "",
          "kategori": "SALDO",
          "harga": "Rp. 200.550",
          "hargaInt": 200500,
          "ket": "",
          "nominal": "SALDO UNIKQU ,",
          "urutan": 0,
          "poin": "0"
        },
        {
          "keterangan": "SALDO UNIKQU 250,000",
          "kodeTransaksi": "UNIKQU250",
          "status": "",
          "kategori": "SALDO",
          "harga": "Rp. 250.550",
          "hargaInt": 250500,
          "ket": "",
          "nominal": "SALDO UNIKQU ,",
          "urutan": 0,
          "poin": "0"
        },
        {
          "keterangan": "SALDO UNIKQU 300,000",
          "kodeTransaksi": "UNIKQU300",
          "status": "",
          "kategori": "SALDO",
          "harga": "Rp. 300.550",
          "hargaInt": 300500,
          "ket": "",
          "nominal": "SALDO UNIKQU ,",
          "urutan": 0,
          "poin": "0"
        },
        {
          "keterangan": "SALDO UNIKQU 500,000",
          "kodeTransaksi": "UNIKQU500",
          "status": "",
          "kategori": "SALDO",
          "harga": "Rp. 500.550",
          "hargaInt": 500500,
          "ket": "",
          "nominal": "SALDO UNIKQU ,",
          "urutan": 0,
          "poin": "0"
        }
      ]
    },
    {
      "nama": "SALDO GRAB",
      "image": "http://192.168.5.6/api/image/app/e-money/saldo_grab.png",
      "kode_operator": "GB",
      "hint": "Contoh : 081234567890",
      "hintTitle": "Nomor Handphone",
      "keyboardNomor": true,
      "detail": [
        {
          "keterangan": "Grab Pay 10.000",
          "kodeTransaksi": "GB10",
          "status": "",
          "kategori": "Grab",
          "harga": "Rp. 12.050",
          "hargaInt": 12000,
          "ket": "",
          "nominal": "Grab Pay",
          "urutan": 0,
          "poin": "0"
        },
        {
          "keterangan": "Grab Pay 20.000",
          "kodeTransaksi": "GB20",
          "status": "",
          "kategori": "Grab",
          "harga": "Rp. 22.050",
          "hargaInt": 22000,
          "ket": "",
          "nominal": "Grab Pay",
          "urutan": 0,
          "poin": "0"
        },
        {
          "keterangan": "Grab Pay 25.000",
          "kodeTransaksi": "GB25",
          "status": "",
          "kategori": "Grab",
          "harga": "Rp. 27.050",
          "hargaInt": 27000,
          "ket": "",
          "nominal": "Grab Pay",
          "urutan": 0,
          "poin": "0"
        },
        {
          "keterangan": "Grab Pay 50.000",
          "kodeTransaksi": "GB50",
          "status": "",
          "kategori": "Grab",
          "harga": "Rp. 51.300",
          "hargaInt": 51250,
          "ket": "",
          "nominal": "Grab Pay",
          "urutan": 0,
          "poin": "0"
        },
        {
          "keterangan": "Grab Pay 100.000",
          "kodeTransaksi": "GB100",
          "status": "",
          "kategori": "Grab",
          "harga": "Rp. 102.050",
          "hargaInt": 102000,
          "ket": "",
          "nominal": "Grab Pay",
          "urutan": 0,
          "poin": "0"
        },
        {
          "keterangan": "Grab Pay 150.000",
          "kodeTransaksi": "GB150",
          "status": "",
          "kategori": "Grab",
          "harga": "Rp. 152.050",
          "hargaInt": 152000,
          "ket": "",
          "nominal": "Grab Pay",
          "urutan": 0,
          "poin": "0"
        },
        {
          "keterangan": "Grab Pay 200.000",
          "kodeTransaksi": "GB200",
          "status": "",
          "kategori": "Grab",
          "harga": "Rp. 201.800",
          "hargaInt": 201750,
          "ket": "",
          "nominal": "Grab Pay",
          "urutan": 0,
          "poin": "0"
        },
        {
          "keterangan": "Grab Pay 300.000",
          "kodeTransaksi": "GB300",
          "status": "",
          "kategori": "Grab",
          "harga": "Rp. 302.050",
          "hargaInt": 302000,
          "ket": "",
          "nominal": "Grab Pay",
          "urutan": 0,
          "poin": "0"
        },
        {
          "keterangan": "Grab Pay 500.000",
          "kodeTransaksi": "GB500",
          "status": "",
          "kategori": "Grab",
          "harga": "Rp. 502.050",
          "hargaInt": 502000,
          "ket": "",
          "nominal": "Grab Pay",
          "urutan": 0,
          "poin": "0"
        }
      ]
    },
    {
      "nama": "SALDO GOPAY",
      "image": "http://192.168.5.6/api/image/app/e-money/saldo_gopay.png",
      "kode_operator": "GP",
      "hint": "Contoh : 081234567890",
      "hintTitle": "Nomor Handphone",
      "keyboardNomor": true,
      "detail": [
        {
          "keterangan": "GoPay Penumpang 10.000",
          "kodeTransaksi": "GP10",
          "status": "",
          "kategori": "GoPay",
          "harga": "Rp. 11.550",
          "hargaInt": 11500,
          "ket": "",
          "nominal": "GoPay Penumpang",
          "urutan": 0,
          "poin": "0"
        },
        {
          "keterangan": "GoPay Penumpang 20.000",
          "kodeTransaksi": "GP20",
          "status": "",
          "kategori": "GoPay",
          "harga": "Rp. 21.550",
          "hargaInt": 21500,
          "ket": "",
          "nominal": "GoPay Penumpang",
          "urutan": 0,
          "poin": "0"
        },
        {
          "keterangan": "GoPay Penumpang 25.000",
          "kodeTransaksi": "GP25",
          "status": "",
          "kategori": "GoPay",
          "harga": "Rp. 26.550",
          "hargaInt": 26500,
          "ket": "",
          "nominal": "GoPay Penumpang",
          "urutan": 0,
          "poin": "0"
        },
        {
          "keterangan": "GoPay Penumpang 50.000",
          "kodeTransaksi": "GP50",
          "status": "",
          "kategori": "GoPay",
          "harga": "Rp. 51.550",
          "hargaInt": 51500,
          "ket": "",
          "nominal": "GoPay Penumpang",
          "urutan": 0,
          "poin": "0"
        },
        {
          "keterangan": "GoPay Penumpang 75.000",
          "kodeTransaksi": "GP75",
          "status": "",
          "kategori": "GoPay",
          "harga": "Rp. 76.550",
          "hargaInt": 76500,
          "ket": "",
          "nominal": "GoPay Penumpang",
          "urutan": 0,
          "poin": "0"
        },
        {
          "keterangan": "GoPay Penumpang 100.000",
          "kodeTransaksi": "GP100",
          "status": "",
          "kategori": "GoPay",
          "harga": "Rp. 101.550",
          "hargaInt": 101500,
          "ket": "",
          "nominal": "GoPay Penumpang",
          "urutan": 0,
          "poin": "0"
        },
        {
          "keterangan": "GoPay Penumpang 150.000",
          "kodeTransaksi": "GP150",
          "status": "",
          "kategori": "GoPay",
          "harga": "Rp. 151.550",
          "hargaInt": 151500,
          "ket": "",
          "nominal": "GoPay Penumpang",
          "urutan": 0,
          "poin": "0"
        },
        {
          "keterangan": "GoPay Penumpang 200.000",
          "kodeTransaksi": "GP200",
          "status": "",
          "kategori": "GoPay",
          "harga": "Rp. 201.550",
          "hargaInt": 201500,
          "ket": "",
          "nominal": "GoPay Penumpang",
          "urutan": 0,
          "poin": "0"
        },
        {
          "keterangan": "GoPay Penumpang 250.000",
          "kodeTransaksi": "GP250",
          "status": "",
          "kategori": "GoPay",
          "harga": "Rp. 251.550",
          "hargaInt": 251500,
          "ket": "",
          "nominal": "GoPay Penumpang",
          "urutan": 0,
          "poin": "0"
        },
        {
          "keterangan": "GoPay Penumpang 300.000",
          "kodeTransaksi": "GP300",
          "status": "",
          "kategori": "GoPay",
          "harga": "Rp. 301.550",
          "hargaInt": 301500,
          "ket": "",
          "nominal": "GoPay Penumpang",
          "urutan": 0,
          "poin": "0"
        },
        {
          "keterangan": "GoPay Penumpang 400.000",
          "kodeTransaksi": "GP400",
          "status": "",
          "kategori": "GoPay",
          "harga": "Rp. 401.550",
          "hargaInt": 401500,
          "ket": "",
          "nominal": "GoPay Penumpang",
          "urutan": 0,
          "poin": "0"
        },
        {
          "keterangan": "GoPay Penumpang 500.000",
          "kodeTransaksi": "GP500",
          "status": "",
          "kategori": "GoPay",
          "harga": "Rp. 501.550",
          "hargaInt": 501500,
          "ket": "",
          "nominal": "GoPay Penumpang",
          "urutan": 0,
          "poin": "0"
        },
        {
          "keterangan": "GoPay Driver 5.000",
          "kodeTransaksi": "GPD5",
          "status": "",
          "kategori": "GoPay",
          "harga": "Rp. 7.050",
          "hargaInt": 7000,
          "ket": "",
          "nominal": "GoPay Driver",
          "urutan": 1,
          "poin": "0"
        },
        {
          "keterangan": "GoPay Driver 10.000",
          "kodeTransaksi": "GPD10",
          "status": "",
          "kategori": "GoPay",
          "harga": "Rp. 12.050",
          "hargaInt": 12000,
          "ket": "",
          "nominal": "GoPay Driver",
          "urutan": 1,
          "poin": "0"
        },
        {
          "keterangan": "GoPay Driver 20.000",
          "kodeTransaksi": "GPD20",
          "status": "",
          "kategori": "GoPay",
          "harga": "Rp. 22.050",
          "hargaInt": 22000,
          "ket": "",
          "nominal": "GoPay Driver",
          "urutan": 1,
          "poin": "0"
        },
        {
          "keterangan": "GoPay Driver 25.000",
          "kodeTransaksi": "GPD25",
          "status": "",
          "kategori": "GoPay",
          "harga": "Rp. 27.050",
          "hargaInt": 27000,
          "ket": "",
          "nominal": "GoPay Driver",
          "urutan": 1,
          "poin": "0"
        },
        {
          "keterangan": "GoPay Driver 50.000",
          "kodeTransaksi": "GPD50",
          "status": "",
          "kategori": "GoPay",
          "harga": "Rp. 52.050",
          "hargaInt": 52000,
          "ket": "",
          "nominal": "GoPay Driver",
          "urutan": 1,
          "poin": "0"
        },
        {
          "keterangan": "GoPay Driver 75.000",
          "kodeTransaksi": "GPD75",
          "status": "",
          "kategori": "GoPay",
          "harga": "Rp. 77.050",
          "hargaInt": 77000,
          "ket": "",
          "nominal": "GoPay Driver",
          "urutan": 1,
          "poin": "0"
        },
        {
          "keterangan": "GoPay Driver 100.000",
          "kodeTransaksi": "GPD100",
          "status": "",
          "kategori": "GoPay",
          "harga": "Rp. 102.050",
          "hargaInt": 102000,
          "ket": "",
          "nominal": "GoPay Driver",
          "urutan": 1,
          "poin": "0"
        },
        {
          "keterangan": "GoPay Driver 150.000",
          "kodeTransaksi": "GPD150",
          "status": "",
          "kategori": "GoPay",
          "harga": "Rp. 152.050",
          "hargaInt": 152000,
          "ket": "",
          "nominal": "GoPay Driver",
          "urutan": 1,
          "poin": "0"
        },
        {
          "keterangan": "GoPay Driver 200.000",
          "kodeTransaksi": "GPD200",
          "status": "",
          "kategori": "GoPay",
          "harga": "Rp. 202.050",
          "hargaInt": 202000,
          "ket": "",
          "nominal": "GoPay Driver",
          "urutan": 1,
          "poin": "0"
        },
        {
          "keterangan": "GoPay Driver 250.000",
          "kodeTransaksi": "GPD250",
          "status": "",
          "kategori": "GoPay",
          "harga": "Rp. 252.050",
          "hargaInt": 252000,
          "ket": "",
          "nominal": "GoPay Driver",
          "urutan": 1,
          "poin": "0"
        },
        {
          "keterangan": "GoPay Driver 300.000",
          "kodeTransaksi": "GPD300",
          "status": "",
          "kategori": "GoPay",
          "harga": "Rp. 302.050",
          "hargaInt": 302000,
          "ket": "",
          "nominal": "GoPay Driver",
          "urutan": 1,
          "poin": "0"
        },
        {
          "keterangan": "GoPay Driver 400.000",
          "kodeTransaksi": "GPD400",
          "status": "",
          "kategori": "GoPay",
          "harga": "Rp. 402.550",
          "hargaInt": 402500,
          "ket": "",
          "nominal": "GoPay Driver",
          "urutan": 1,
          "poin": "0"
        },
        {
          "keterangan": "GoPay Driver 500.000",
          "kodeTransaksi": "GPD500",
          "status": "",
          "kategori": "GoPay",
          "harga": "Rp. 502.550",
          "hargaInt": 502500,
          "ket": "",
          "nominal": "GoPay Driver",
          "urutan": 1,
          "poin": "0"
        }
      ]
    },
    {
      "nama": "SALDO MTIX",
      "image": "http://192.168.5.6/api/image/app/e-money/mtix.png",
      "kode_operator": "MTIX",
      "hint": "Contoh : 081234567890",
      "hintTitle": "Nomor Handphone",
      "keyboardNomor": true,
      "detail": [
        {
          "keterangan": "SALDO MTIX 100,000",
          "kodeTransaksi": "MTIX100",
          "status": "",
          "kategori": "SALDO",
          "harga": "Rp. 107.050",
          "hargaInt": 107000,
          "ket": "",
          "nominal": "SALDO MTIX ,",
          "urutan": 0,
          "poin": "0"
        },
        {
          "keterangan": "SALDO MTIX 200,000",
          "kodeTransaksi": "MTIX200",
          "status": "",
          "kategori": "SALDO",
          "harga": "Rp. 207.050",
          "hargaInt": 207000,
          "ket": "",
          "nominal": "SALDO MTIX ,",
          "urutan": 0,
          "poin": "0"
        },
        {
          "keterangan": "SALDO MTIX 300,000",
          "kodeTransaksi": "MTIX300",
          "status": "",
          "kategori": "SALDO",
          "harga": "Rp. 307.050",
          "hargaInt": 307000,
          "ket": "",
          "nominal": "SALDO MTIX ,",
          "urutan": 0,
          "poin": "0"
        }
      ]
    },
    {
      "nama": "SALDO OVO",
      "image": "http://192.168.5.6/api/image/app/e-money/ovo.png",
      "kode_operator": "OVO",
      "hint": "Contoh : 081234567890",
      "hintTitle": "Nomor Handphone",
      "keyboardNomor": true,
      "detail": [
        {
          "keterangan": "SALDO OVO 10,000",
          "kodeTransaksi": "OVO10",
          "status": "",
          "kategori": "SALDO",
          "harga": "Rp. 11.300",
          "hargaInt": 11250,
          "ket": "",
          "nominal": "SALDO OVO ,",
          "urutan": 0,
          "poin": "0"
        },
        {
          "keterangan": "SALDO OVO 20,000",
          "kodeTransaksi": "OVO20",
          "status": "",
          "kategori": "SALDO",
          "harga": "Rp. 21.300",
          "hargaInt": 21250,
          "ket": "",
          "nominal": "SALDO OVO ,",
          "urutan": 0,
          "poin": "0"
        },
        {
          "keterangan": "SALDO OVO 25,000",
          "kodeTransaksi": "OVO25",
          "status": "",
          "kategori": "SALDO",
          "harga": "Rp. 26.300",
          "hargaInt": 26250,
          "ket": "",
          "nominal": "SALDO OVO ,",
          "urutan": 0,
          "poin": "0"
        },
        {
          "keterangan": "SALDO OVO 30.000",
          "kodeTransaksi": "OVO30",
          "status": "",
          "kategori": "SALDO",
          "harga": "Rp. 31.300",
          "hargaInt": 31250,
          "ket": "",
          "nominal": "SALDO OVO",
          "urutan": 0,
          "poin": "0"
        },
        {
          "keterangan": "SALDO OVO 40,000",
          "kodeTransaksi": "OVO40",
          "status": "",
          "kategori": "SALDO",
          "harga": "Rp. 41.300",
          "hargaInt": 41250,
          "ket": "",
          "nominal": "SALDO OVO ,",
          "urutan": 0,
          "poin": "0"
        },
        {
          "keterangan": "SALDO OVO 50,000",
          "kodeTransaksi": "OVO50",
          "status": "",
          "kategori": "SALDO",
          "harga": "Rp. 51.300",
          "hargaInt": 51250,
          "ket": "",
          "nominal": "SALDO OVO ,",
          "urutan": 0,
          "poin": "0"
        },
        {
          "keterangan": "SALDO OVO 75.000",
          "kodeTransaksi": "OVO75",
          "status": "",
          "kategori": "SALDO",
          "harga": "Rp. 76.300",
          "hargaInt": 76250,
          "ket": "",
          "nominal": "SALDO OVO",
          "urutan": 0,
          "poin": "0"
        },
        {
          "keterangan": "SALDO OVO 100,000",
          "kodeTransaksi": "OVO100",
          "status": "",
          "kategori": "SALDO",
          "harga": "Rp. 102.050",
          "hargaInt": 102000,
          "ket": "",
          "nominal": "SALDO OVO ,",
          "urutan": 0,
          "poin": "0"
        },
        {
          "keterangan": "SALDO OVO 125.000",
          "kodeTransaksi": "OVO125",
          "status": "",
          "kategori": "SALDO",
          "harga": "Rp. 126.300",
          "hargaInt": 126250,
          "ket": "",
          "nominal": "SALDO OVO",
          "urutan": 0,
          "poin": "0"
        },
        {
          "keterangan": "SALDO OVO 150.000",
          "kodeTransaksi": "OVO150",
          "status": "",
          "kategori": "SALDO",
          "harga": "Rp. 151.300",
          "hargaInt": 151250,
          "ket": "",
          "nominal": "SALDO OVO",
          "urutan": 0,
          "poin": "0"
        },
        {
          "keterangan": "SALDO OVO 175.000",
          "kodeTransaksi": "OVO175",
          "status": "",
          "kategori": "SALDO",
          "harga": "Rp. 176.300",
          "hargaInt": 176250,
          "ket": "",
          "nominal": "SALDO OVO",
          "urutan": 0,
          "poin": "0"
        },
        {
          "keterangan": "SALDO OVO 200,000",
          "kodeTransaksi": "OVO200",
          "status": "",
          "kategori": "SALDO",
          "harga": "Rp. 201.800",
          "hargaInt": 201750,
          "ket": "",
          "nominal": "SALDO OVO ,",
          "urutan": 0,
          "poin": "0"
        },
        {
          "keterangan": "SALDO OVO 225.000",
          "kodeTransaksi": "OVO225",
          "status": "",
          "kategori": "SALDO",
          "harga": "Rp. 226.300",
          "hargaInt": 226250,
          "ket": "",
          "nominal": "SALDO OVO",
          "urutan": 0,
          "poin": "0"
        },
        {
          "keterangan": "SALDO OVO 250.000",
          "kodeTransaksi": "OVO250",
          "status": "",
          "kategori": "SALDO",
          "harga": "Rp. 251.300",
          "hargaInt": 251250,
          "ket": "",
          "nominal": "SALDO OVO",
          "urutan": 0,
          "poin": "0"
        },
        {
          "keterangan": "SALDO OVO 300.000",
          "kodeTransaksi": "OVO300",
          "status": "",
          "kategori": "SALDO",
          "harga": "Rp. 301.300",
          "hargaInt": 301250,
          "ket": "",
          "nominal": "SALDO OVO",
          "urutan": 0,
          "poin": "0"
        },
        {
          "keterangan": "SALDO OVO 400.000",
          "kodeTransaksi": "OVO400",
          "status": "",
          "kategori": "SALDO",
          "harga": "Rp. 401.300",
          "hargaInt": 401250,
          "ket": "",
          "nominal": "SALDO OVO",
          "urutan": 0,
          "poin": "0"
        },
        {
          "keterangan": "SALDO OVO 500,000",
          "kodeTransaksi": "OVO500",
          "status": "",
          "kategori": "SALDO",
          "harga": "Rp. 502.050",
          "hargaInt": 502000,
          "ket": "",
          "nominal": "SALDO OVO ,",
          "urutan": 0,
          "poin": "0"
        },
        {
          "keterangan": "SALDO OVO 600.000",
          "kodeTransaksi": "OVO600",
          "status": "",
          "kategori": "SALDO",
          "harga": "Rp. 602.050",
          "hargaInt": 602000,
          "ket": "",
          "nominal": "SALDO OVO",
          "urutan": 0,
          "poin": "0"
        },
        {
          "keterangan": "SALDO OVO 700.000",
          "kodeTransaksi": "OVO700",
          "status": "",
          "kategori": "SALDO",
          "harga": "Rp. 702.050",
          "hargaInt": 702000,
          "ket": "",
          "nominal": "SALDO OVO",
          "urutan": 0,
          "poin": "0"
        },
        {
          "keterangan": "SALDO OVO 800.000",
          "kodeTransaksi": "OVO800",
          "status": "",
          "kategori": "SALDO",
          "harga": "Rp. 802.050",
          "hargaInt": 802000,
          "ket": "",
          "nominal": "SALDO OVO",
          "urutan": 0,
          "poin": "0"
        },
        {
          "keterangan": "SALDO OVO 900.000",
          "kodeTransaksi": "OVO900",
          "status": "",
          "kategori": "SALDO",
          "harga": "Rp. 902.050",
          "hargaInt": 902000,
          "ket": "",
          "nominal": "SALDO OVO",
          "urutan": 0,
          "poin": "0"
        },
        {
          "keterangan": "SALDO OVO 1.000.000",
          "kodeTransaksi": "OVO1000",
          "status": "",
          "kategori": "SALDO",
          "harga": "Rp. 1.002.050",
          "hargaInt": 1002000,
          "ket": "",
          "nominal": "SALDO OVO",
          "urutan": 0,
          "poin": "0"
        }
      ]
    },
    {
      "nama": "SALDO TCASH",
      "image": "http://192.168.5.6/api/image/app/e-money/tcash.png",
      "kode_operator": "TCASH",
      "hint": "Contoh : 081234567890",
      "hintTitle": "Nomor Handphone",
      "keyboardNomor": true,
      "detail": [
        {
          "keterangan": "SALDO TCASH 10,000",
          "kodeTransaksi": "TCASH10",
          "status": "",
          "kategori": "SALDO",
          "harga": "Rp. 11.300",
          "hargaInt": 11250,
          "ket": "",
          "nominal": "SALDO TCASH ,",
          "urutan": 0,
          "poin": "0"
        },
        {
          "keterangan": "SALDO TCASH 20,000",
          "kodeTransaksi": "TCASH20",
          "status": "",
          "kategori": "SALDO",
          "harga": "Rp. 21.300",
          "hargaInt": 21250,
          "ket": "",
          "nominal": "SALDO TCASH ,",
          "urutan": 0,
          "poin": "0"
        },
        {
          "keterangan": "SALDO TCASH 30,000",
          "kodeTransaksi": "TCASH30",
          "status": "",
          "kategori": "SALDO",
          "harga": "Rp. 31.300",
          "hargaInt": 31250,
          "ket": "",
          "nominal": "SALDO TCASH ,",
          "urutan": 0,
          "poin": "0"
        },
        {
          "keterangan": "SALDO TCASH 40,000",
          "kodeTransaksi": "TCASH40",
          "status": "",
          "kategori": "SALDO",
          "harga": "Rp. 41.300",
          "hargaInt": 41250,
          "ket": "",
          "nominal": "SALDO TCASH ,",
          "urutan": 0,
          "poin": "0"
        },
        {
          "keterangan": "SALDO TCASH 50,000",
          "kodeTransaksi": "TCASH50",
          "status": "",
          "kategori": "SALDO",
          "harga": "Rp. 51.300",
          "hargaInt": 51250,
          "ket": "",
          "nominal": "SALDO TCASH ,",
          "urutan": 0,
          "poin": "0"
        },
        {
          "keterangan": "SALDO TCASH 60,000",
          "kodeTransaksi": "TCASH60",
          "status": "",
          "kategori": "SALDO",
          "harga": "Rp. 61.300",
          "hargaInt": 61250,
          "ket": "",
          "nominal": "SALDO TCASH ,",
          "urutan": 0,
          "poin": "0"
        },
        {
          "keterangan": "SALDO TCASH 70,000",
          "kodeTransaksi": "TCASH70",
          "status": "",
          "kategori": "SALDO",
          "harga": "Rp. 71.300",
          "hargaInt": 71250,
          "ket": "",
          "nominal": "SALDO TCASH ,",
          "urutan": 0,
          "poin": "0"
        },
        {
          "keterangan": "SALDO TCASH 80,000",
          "kodeTransaksi": "TCASH80",
          "status": "",
          "kategori": "SALDO",
          "harga": "Rp. 81.300",
          "hargaInt": 81250,
          "ket": "",
          "nominal": "SALDO TCASH ,",
          "urutan": 0,
          "poin": "0"
        },
        {
          "keterangan": "SALDO TCASH 90,000",
          "kodeTransaksi": "TCASH90",
          "status": "",
          "kategori": "SALDO",
          "harga": "Rp. 91.300",
          "hargaInt": 91250,
          "ket": "",
          "nominal": "SALDO TCASH ,",
          "urutan": 0,
          "poin": "0"
        },
        {
          "keterangan": "SALDO TCASH 100,000",
          "kodeTransaksi": "TCASH100",
          "status": "",
          "kategori": "SALDO",
          "harga": "Rp. 102.300",
          "hargaInt": 102250,
          "ket": "",
          "nominal": "SALDO TCASH ,",
          "urutan": 0,
          "poin": "0"
        },
        {
          "keterangan": "SALDO TCASH 150,000",
          "kodeTransaksi": "TCASH150",
          "status": "",
          "kategori": "SALDO",
          "harga": "Rp. 152.300",
          "hargaInt": 152250,
          "ket": "",
          "nominal": "SALDO TCASH ,",
          "urutan": 0,
          "poin": "0"
        },
        {
          "keterangan": "SALDO TCASH 200,000",
          "kodeTransaksi": "TCASH200",
          "status": "",
          "kategori": "SALDO",
          "harga": "Rp. 202.300",
          "hargaInt": 202250,
          "ket": "",
          "nominal": "SALDO TCASH ,",
          "urutan": 0,
          "poin": "0"
        },
        {
          "keterangan": "SALDO TCASH 250.000",
          "kodeTransaksi": "TCASH250",
          "status": "",
          "kategori": "SALDO",
          "harga": "Rp. 252.300",
          "hargaInt": 252250,
          "ket": "",
          "nominal": "SALDO TCASH",
          "urutan": 0,
          "poin": "0"
        },
        {
          "keterangan": "SALDO TCASH 300,000",
          "kodeTransaksi": "TCASH300",
          "status": "",
          "kategori": "SALDO",
          "harga": "Rp. 302.300",
          "hargaInt": 302250,
          "ket": "",
          "nominal": "SALDO TCASH ,",
          "urutan": 0,
          "poin": "0"
        },
        {
          "keterangan": "SALDO TCASH 400,000",
          "kodeTransaksi": "TCASH400",
          "status": "",
          "kategori": "SALDO",
          "harga": "Rp. 402.300",
          "hargaInt": 402250,
          "ket": "",
          "nominal": "SALDO TCASH ,",
          "urutan": 0,
          "poin": "0"
        },
        {
          "keterangan": "SALDO TCASH 500,000",
          "kodeTransaksi": "TCASH500",
          "status": "",
          "kategori": "SALDO",
          "harga": "Rp. 502.300",
          "hargaInt": 502250,
          "ket": "",
          "nominal": "SALDO TCASH ,",
          "urutan": 0,
          "poin": "0"
        },
        {
          "keterangan": "SALDO TCASH 600,000",
          "kodeTransaksi": "TCASH600",
          "status": "",
          "kategori": "SALDO",
          "harga": "Rp. 602.300",
          "hargaInt": 602250,
          "ket": "",
          "nominal": "SALDO TCASH ,",
          "urutan": 0,
          "poin": "0"
        },
        {
          "keterangan": "SALDO TCASH 700,000",
          "kodeTransaksi": "TCASH700",
          "status": "",
          "kategori": "SALDO",
          "harga": "Rp. 702.300",
          "hargaInt": 702250,
          "ket": "",
          "nominal": "SALDO TCASH ,",
          "urutan": 0,
          "poin": "0"
        },
        {
          "keterangan": "SALDO TCASH 800,000",
          "kodeTransaksi": "TCASH800",
          "status": "",
          "kategori": "SALDO",
          "harga": "Rp. 802.300",
          "hargaInt": 802250,
          "ket": "",
          "nominal": "SALDO TCASH ,",
          "urutan": 0,
          "poin": "0"
        },
        {
          "keterangan": "SALDO TCASH 900,000",
          "kodeTransaksi": "TCASH900",
          "status": "",
          "kategori": "SALDO",
          "harga": "Rp. 902.300",
          "hargaInt": 902250,
          "ket": "",
          "nominal": "SALDO TCASH ,",
          "urutan": 0,
          "poin": "0"
        },
        {
          "keterangan": "SALDO TCASH 1.000,000",
          "kodeTransaksi": "TCASH1000",
          "status": "",
          "kategori": "SALDO",
          "harga": "Rp. 1.002.300",
          "hargaInt": 1002250,
          "ket": "",
          "nominal": "SALDO TCASH ,",
          "urutan": 0,
          "poin": "0"
        }
      ]
    },
    {
      "nama": "SALDO TOKOPEDIA",
      "image": "http://192.168.5.6/api/image/app/e-money/toped.png",
      "kode_operator": "TOPED",
      "hint": "Contoh : 081234567890",
      "hintTitle": "Nomor Handphone",
      "keyboardNomor": true,
      "detail": [
        {
          "keterangan": "SALDO TOKOPEDIA 10,000",
          "kodeTransaksi": "TOPED10",
          "status": "",
          "kategori": "SALDO",
          "harga": "Rp. 11.300",
          "hargaInt": 11250,
          "ket": "",
          "nominal": "SALDO TOKOPEDIA ,",
          "urutan": 0,
          "poin": "0"
        },
        {
          "keterangan": "SALDO TOKOPEDIA 20,000",
          "kodeTransaksi": "TOPED20",
          "status": "",
          "kategori": "SALDO",
          "harga": "Rp. 21.300",
          "hargaInt": 21250,
          "ket": "",
          "nominal": "SALDO TOKOPEDIA ,",
          "urutan": 0,
          "poin": "0"
        },
        {
          "keterangan": "SALDO TOKOPEDIA 25,000",
          "kodeTransaksi": "TOPED25",
          "status": "",
          "kategori": "SALDO",
          "harga": "Rp. 26.300",
          "hargaInt": 26250,
          "ket": "",
          "nominal": "SALDO TOKOPEDIA ,",
          "urutan": 0,
          "poin": "0"
        },
        {
          "keterangan": "SALDO TOKOPEDIA 40,000",
          "kodeTransaksi": "TOPED40",
          "status": "",
          "kategori": "SALDO",
          "harga": "Rp. 41.300",
          "hargaInt": 41250,
          "ket": "",
          "nominal": "SALDO TOKOPEDIA ,",
          "urutan": 0,
          "poin": "0"
        },
        {
          "keterangan": "SALDO TOKOPEDIA 50,000",
          "kodeTransaksi": "TOPED50",
          "status": "",
          "kategori": "SALDO",
          "harga": "Rp. 51.300",
          "hargaInt": 51250,
          "ket": "",
          "nominal": "SALDO TOKOPEDIA ,",
          "urutan": 0,
          "poin": "0"
        },
        {
          "keterangan": "SALDO TOKOPEDIA 100,000",
          "kodeTransaksi": "TOPED100",
          "status": "",
          "kategori": "SALDO",
          "harga": "Rp. 102.050",
          "hargaInt": 102000,
          "ket": "",
          "nominal": "SALDO TOKOPEDIA ,",
          "urutan": 0,
          "poin": "0"
        },
        {
          "keterangan": "SALDO TOKOPEDIA 200,000",
          "kodeTransaksi": "TOPED200",
          "status": "",
          "kategori": "SALDO",
          "harga": "Rp. 201.800",
          "hargaInt": 201750,
          "ket": "",
          "nominal": "SALDO TOKOPEDIA ,",
          "urutan": 0,
          "poin": "0"
        },
        {
          "keterangan": "SALDO TOKOPEDIA 500,000",
          "kodeTransaksi": "TOPED500",
          "status": "",
          "kategori": "SALDO",
          "harga": "Rp. 502.050",
          "hargaInt": 502000,
          "ket": "",
          "nominal": "SALDO TOKOPEDIA",
          "urutan": 0,
          "poin": "0"
        }
      ]
    }
  ]
}